OneLLM/OneLLM.py
OneLLM/__init__.py
OneLLMAPI/OneLLMAPI.py
OneLLMAPI/__init__.py
onellmapi-1.0.dist-info/METADATA
onellmapi-1.0.dist-info/WHEEL
onellmapi-1.0.dist-info/top_level.txt
onellmapi-1.0.dist-info/RECORD
