Metadata-Version: 2.4
Name: OneLLMAPI
Version: 1.0
Summary: A package that integrates the APIs of multiple major language model manufacturers.
Home-page: https://gitee.com/DragonLan666/OneLLM
Author: Zhang Lan,Zhou Yu Qing
Author-email: dragonlan6@outlook.com
License: MIT
Classifier: Programming Language :: Python :: 3
Classifier: License :: OSI Approved :: MIT License
Classifier: Operating System :: OS Independent
Requires-Python: >=3.8
Requires-Dist: copy
Requires-Dist: requests
Requires-Dist: hashlib
Requires-Dist: time
Requires-Dist: json
Requires-Dist: openai
Requires-Dist: dashscope
Requires-Dist: baidubce
Dynamic: author
Dynamic: author-email
Dynamic: classifier
Dynamic: description
Dynamic: description-content-type
Dynamic: home-page
Dynamic: license
Dynamic: requires-dist
Dynamic: requires-python
Dynamic: summary
